yamicache/__init__.py
yamicache/__init__.pyi
yamicache/py.typed
yamicache/yamicache.py
yamicache/yamicache.pyi
yamicache-0.7.3.dist-info/LICENSE
yamicache-0.7.3.dist-info/METADATA
yamicache-0.7.3.dist-info/WHEEL
yamicache-0.7.3.dist-info/RECORD
