Metadata-Version: 2.1
Name: yamicache
Version: 0.7.3
Summary: Yet another in-memory caching package
Home-page: https://github.com/mtik00/yamicache
License: MIT
Author: Timothy McFadden
Author-email: mtik00@users.noreply.github.com
Requires-Python: >=3.11,<4.0
Classifier: Development Status :: 3 - Alpha
Classifier: Intended Audience :: Developers
Classifier: License :: OSI Approved :: MIT License
Classifier: Natural Language :: English
Classifier: Programming Language :: Python :: 3
Classifier: Programming Language :: Python :: 3.11
Classifier: Programming Language :: Python :: 3
Project-URL: Documentation, https://yamicache.readthedocs.io
Project-URL: Repository, https://github.com/mtik00/yamicache
